life123/__init__.py
life123/bio_sim_1d.py
life123/bio_sim_2d.py
life123/bio_sim_3d.py
life123/chem_data.py
life123/collections.py
life123/diagnostics.py
life123/history.py
life123/html_log.py
life123/numerical.py
life123/reaction_kinetics.py
life123/reactions.py
life123/thermodynamics.py
life123/uniform_compartment.py
life123/visualization/colors.py
life123/visualization/graphic_log.py
life123/visualization/plotly_helper.py
life123/visualization/py_graph_visual.py
life123-1.0rc6.dist-info/METADATA
life123-1.0rc6.dist-info/WHEEL
life123-1.0rc6.dist-info/licenses/LICENSE.txt
life123-1.0rc6.dist-info/RECORD
