Metadata-Version: 2.4
Name: life123
Version: 1.0rc6
Summary: Dynamical Modeling of Biological Systems - Quantitative Reactomics
Project-URL: Homepage, https://life123.science
Project-URL: Home-page, https://life123.science
Project-URL: Bug Tracker, https://github.com/BrainAnnex/life123/issues
Project-URL: Source, https://github.com/BrainAnnex/life123
Project-URL: Documentation, https://life123.science
Author: Julian West Life123.science
Maintainer-email: julian@brainannex.org
License-Expression: MIT
License-File: LICENSE.txt
Keywords: dynamical modeling,quantitative reactomics,reactions and diffusion,systems biology
Classifier: License :: OSI Approved :: MIT License
Classifier: Operating System :: OS Independent
Classifier: Programming Language :: Python :: 3
Requires-Python: >=3.9
Requires-Dist: numpy~=1.26.4
Requires-Dist: pandas~=1.5.3
Requires-Dist: plotly~=5.24.1
Requires-Dist: scipy~=1.13.1
